{
    "hasNextPage": true,
    "data": [
        {
            "id": 2309,
            "title": "Introduction to Spark Streaming",
            "url": "https://www.analyticsvidhya.com/blog/2022/08/introduction-to-spark-streaming/",
            "authors": "Aman Preet Gulati",
            "tags": "Beginner, Data Engineering, Spark",
            "publishedOn": "2022-08-14T00:00:00",
            "description": "Spark Streaming combination deals with a static dataset and a live dataset with interactive queries, providing\u00a0native support to end users.",
            "thumbnail": "https://cdn.analyticsvidhya.com/wp-content/uploads/2022/05/3.png",
            "sourceId": 3,
            "source": "Analytics Vidhya Blog"
        },
        {
            "id": 2310,
            "title": "Step-by-step Explanation of Text Classification",
            "url": "https://www.analyticsvidhya.com/blog/2022/08/step-by-step-explanation-of-text-classification/",
            "authors": "Adnan Afzal",
            "tags": "Beginner, Machine Learning, NLP, Python",
            "publishedOn": "2022-08-14T00:00:00",
            "description": "Text classification is a machine learning algorithm that allocates categories to the input text with predefined and customizable links",
            "thumbnail": "https://cdn.analyticsvidhya.com/wp-content/uploads/2021/07/80352nlp.jpg",
            "sourceId": 3,
            "source": "Analytics Vidhya Blog"
        },
        {
            "id": 8529,
            "title": "Why Initialize a Neural Network with Random Weights?",
            "url": "https://machinelearningmastery.com/why-initialize-a-neural-network-with-random-weights/",
            "authors": "Jason Brownlee",
            "tags": "Deep Learning",
            "publishedOn": "2022-08-14T00:00:00",
            "description": "The weights of artificial neural networks must be initialized to small random numbers. This is because this is an expectation of the stochastic optimization algorithm used to train the model, called stochastic gradient descent. To understand this approach to problem solving, you must first understand the role of nondeterministic and randomized algorithms as well as [\u2026]",
            "thumbnail": "https://machinelearningmastery.com/wp-content/uploads/2018/08/Why-Initialize-a-Neural-Network-with-Random-Weights.jpg",
            "sourceId": 14,
            "source": "Machine Learning Mastery Blog"
        },
        {
            "id": 10669,
            "title": "The Top 3 Conferences For Data Science and Analytics",
            "url": "https://towardsai.net/p/l/the-top-3-conferences-for-data-science-and-analytics",
            "authors": "Rijul Singh Malik",
            "tags": null,
            "publishedOn": "2022-08-14T00:00:00",
            "description": "Originally published on Towards AI the World's Leading AI and Technology News and Media Company. If you are building an AI-related product or service, we invite you to consider...",
            "thumbnail": "https://cdn-images-1.medium.com/max/1024/0*zRyMl-B94jpuuFbI",
            "sourceId": 19,
            "source": "Towards AI Blog"
        },
        {
            "id": 10670,
            "title": "Build Animatable 3D Models with AI",
            "url": "https://towardsai.net/p/l/build-animatable-3d-models-with-ai",
            "authors": "Louis Bouchard",
            "tags": null,
            "publishedOn": "2022-08-14T00:00:00",
            "description": "Originally published on Towards AI the World's Leading AI and Technology News and Media Company. If you are building an AI-related product or service, we invite you to consider...",
            "thumbnail": "https://cdn-images-1.medium.com/max/822/1*gCNcDgxRkhaFMPctKHl6dQ.gif",
            "sourceId": 19,
            "source": "Towards AI Blog"
        },
        {
            "id": 10671,
            "title": "I Wish I Were Van Gogh\u2026",
            "url": "https://towardsai.net/p/l/i-wish-i-were-van-gogh",
            "authors": "Natasha Mashanovich",
            "tags": null,
            "publishedOn": "2022-08-14T00:00:00",
            "description": "Originally published on Towards AI the World's Leading AI and Technology News and Media Company. If you are building an AI-related product or service, we invite you to consider...",
            "thumbnail": "https://cdn-images-1.medium.com/max/256/1*9BP1r1LdHZ6J-Qn3ndUMXg.jpeg",
            "sourceId": 19,
            "source": "Towards AI Blog"
        },
        {
            "id": 2311,
            "title": "Dealing with outliers using the Z-Score method",
            "url": "https://www.analyticsvidhya.com/blog/2022/08/dealing-with-outliers-using-the-z-score-method/",
            "authors": "Aman Preet Gulati",
            "tags": "Beginner, Data Exploration, Machine Learning, Python, Statistics",
            "publishedOn": "2022-08-13T00:00:00",
            "description": "Outliers detection is widely used method in data science project, as its presence can lead to the development of bad machine learning model.",
            "thumbnail": "https://cdn.analyticsvidhya.com/wp-content/uploads/2021/05/66001when-to-use-data-science-in-seo-5def8e5b1c22c-760x400-1.png",
            "sourceId": 3,
            "source": "Analytics Vidhya Blog"
        },
        {
            "id": 2312,
            "title": "A Comparative Analysis of Community Detection Algorithms",
            "url": "https://www.analyticsvidhya.com/blog/2022/08/a-comparative-analysis-of-community-detection-algorithms/",
            "authors": "Tanisha Mandal",
            "tags": "Algorithm, Beginner, Graphs & Networks, Python",
            "publishedOn": "2022-08-12T00:00:00",
            "description": "Community detection in a network identifies and groups the more\u00a0densely interconnected nodes in a given graph.",
            "thumbnail": "https://cdn.analyticsvidhya.com/wp-content/uploads/2019/10/artificial-neural-network-3501528_960_720.png",
            "sourceId": 3,
            "source": "Analytics Vidhya Blog"
        },
        {
            "id": 2313,
            "title": "Outliers Pruning Using Python",
            "url": "https://www.analyticsvidhya.com/blog/2022/08/outliers-pruning-using-python/",
            "authors": "Aman Preet Gulati",
            "tags": "Beginner, Data Exploration, Machine Learning",
            "publishedOn": "2022-08-12T00:00:00",
            "description": "Outliers pruning on three types of data, i.e., dimensional, two-dimensional, and Curve data, using some statistical methods.",
            "thumbnail": "https://cdn.analyticsvidhya.com/wp-content/uploads/2019/11/interpretable_machine_learning.jpg",
            "sourceId": 3,
            "source": "Analytics Vidhya Blog"
        },
        {
            "id": 8315,
            "title": "Introducing Skops",
            "url": "https://huggingface.co/blog/skops",
            "authors": "merve",
            "tags": null,
            "publishedOn": "2022-08-12T00:00:00",
            "description": "We\u2019re on a journey to advance and democratize artificial intelligence through open source and open science.",
            "thumbnail": "https://huggingface.co/blog/assets/94_skops/introducing_skops.png",
            "sourceId": 11,
            "source": "Huggingface Blog"
        },
        {
            "id": 8316,
            "title": "Hugging Face's TensorFlow Philosophy",
            "url": "https://huggingface.co/blog/tensorflow-philosophy",
            "authors": "rocketknight1",
            "tags": null,
            "publishedOn": "2022-08-12T00:00:00",
            "description": "We\u2019re on a journey to advance and democratize artificial intelligence through open source and open science.",
            "thumbnail": "https://huggingface.co/blog/assets/96_tensorflow_philosophy/thumbnail.png",
            "sourceId": 11,
            "source": "Huggingface Blog"
        },
        {
            "id": 8530,
            "title": "When to Use MLP, CNN, and RNN Neural Networks",
            "url": "https://machinelearningmastery.com/when-to-use-mlp-cnn-and-rnn-neural-networks/",
            "authors": "Jason Brownlee",
            "tags": "Deep Learning",
            "publishedOn": "2022-08-12T00:00:00",
            "description": "What neural network is appropriate for your predictive modeling problem? It can be difficult for a beginner to the field of deep learning to know what type of network to use. There are so many types of networks to choose from and new methods being published and discussed every day. To make things worse, most [\u2026]",
            "thumbnail": "https://machinelearningmastery.com/wp-content/uploads/2018/07/When-to-Use-MLP-CNN-and-RNN-Neural-Networks.jpg",
            "sourceId": 14,
            "source": "Machine Learning Mastery Blog"
        },
        {
            "id": 10672,
            "title": "How Many Different Gender Subtypes Do We Have In Our Brains?",
            "url": "https://towardsai.net/p/l/how-many-different-gender-subtypes-do-we-have-in-our-brains",
            "authors": "Jair Ribeiro",
            "tags": null,
            "publishedOn": "2022-08-12T00:00:00",
            "description": "Originally published on Towards AI the World's Leading AI and Technology News and Media Company. If you are building an AI-related product or service, we invite you to consider...",
            "thumbnail": "https://cdn-images-1.medium.com/max/2600/0*UpGuBX5-7yTyo4ms",
            "sourceId": 19,
            "source": "Towards AI Blog"
        },
        {
            "id": 10673,
            "title": "How Robots Have Evolved",
            "url": "https://towardsai.net/p/l/how-robots-have-evolved",
            "authors": "Rijul Singh Malik",
            "tags": null,
            "publishedOn": "2022-08-12T00:00:00",
            "description": "Originally published on Towards AI the World's Leading AI and Technology News and Media Company. If you are building an AI-related product or service, we invite you to consider...",
            "thumbnail": "https://cdn-images-1.medium.com/max/1024/0*yedBbZIvW7ym-bS_",
            "sourceId": 19,
            "source": "Towards AI Blog"
        },
        {
            "id": 7142,
            "title": "Rax: Composable Learning-to-Rank Using JAX",
            "url": "http://ai.googleblog.com/2022/08/rax-composable-learning-to-rank-using.html",
            "authors": null,
            "tags": null,
            "publishedOn": "2022-08-11T11:22:00-07:00",
            "description": null,
            "thumbnail": "https://blogger.googleusercontent.com/img/b/R29vZ2xl/AVvXsEjGRgP1LpkryGXlwQqs1NhgkLpD8xXlMaVWLlPCDxDahnyIlABUJFLUK3Cdo5BDDDlI04kQ2hQkdqnOVtkr3B_AKl7NAwS0tQJS18XeM3YUNLXleAKIQvhw8330xgbavEa3obBIQ71Eq1tKQUzKxAqiytyF7R4XpHxDeQkUzQCX00lwXsowT59Qqcxscw/s72-c/image3.gif",
            "sourceId": 9,
            "source": "Google AI Blog"
        },
        {
            "id": 141,
            "title": "Build an air quality anomaly detector using Amazon Lookout for Metrics",
            "url": "https://aws.amazon.com/blogs/machine-learning/build-an-air-quality-anomaly-detector-using-amazon-lookout-for-metrics/",
            "authors": "Dhiraj Thakur",
            "tags": "Amazon Lookout for Metrics, Artificial Intelligence",
            "publishedOn": "2022-08-11T00:00:00",
            "description": "Today, air pollution is a familiar environmental issue that creates severe respiratory and heart conditions, which pose serious health threats. Acid rain, depletion of the ozone layer, and global warming are also adverse consequences of air pollution. There is a need for intelligent monitoring and automation in order to prevent severe health issues and in [\u2026]",
            "thumbnail": "https://d2908q01vomqb2.cloudfront.net/f1f836cb4ea6efb2a0b1b99f41ad8b103eff4b59/2022/07/27/ML-7925-image001-1225x630.png",
            "sourceId": 1,
            "source": "Amazon ML Blog"
        },
        {
            "id": 142,
            "title": "Build a GNN-based real-time fraud detection solution using Amazon SageMaker, Amazon Neptune, and the Deep Graph Library",
            "url": "https://aws.amazon.com/blogs/machine-learning/build-a-gnn-based-real-time-fraud-detection-solution-using-amazon-sagemaker-amazon-neptune-and-the-deep-graph-library/",
            "authors": "Jian Zhang, Haozhu Wang, Mengxin Zhu",
            "tags": "Amazon Neptune, Amazon SageMaker, Artificial Intelligence",
            "publishedOn": "2022-08-11T00:00:00",
            "description": "Fraudulent activities severely impact many industries, such as e-commerce, social media, and financial services. Frauds could cause a significant loss for businesses and consumers. American consumers reported losing more than $5.8 billion to frauds in 2021, up more than 70% over 2020. Many techniques have been used to detect fraudsters\u2014rule-based filters, anomaly detection, and machine [\u2026]",
            "thumbnail": "https://d2908q01vomqb2.cloudfront.net/f1f836cb4ea6efb2a0b1b99f41ad8b103eff4b59/2022/08/02/image001.jpg",
            "sourceId": 1,
            "source": "Amazon ML Blog"
        },
        {
            "id": 1630,
            "title": "KDD: Graph neural networks, fairness, and inclusivity",
            "url": "https://www.amazon.science/blog/kdd-graph-neural-networks-fairness-and-inclusivity",
            "authors": "Larry Hardesty",
            "tags": "Machine learning",
            "publishedOn": "2022-08-11T00:00:00",
            "description": "The general chair of this year\u2019s Conference on Knowledge Discovery and Data Mining on what excites him most about the conference program.",
            "thumbnail": "https://assets.amazon.science/dims4/default/a476725/2147483647/strip/true/crop/833x437+0+17/resize/1200x630!/quality/90/?url=http%3A%2F%2Famazon-topics-brightspot.s3.amazonaws.com%2Fscience%2F75%2Fe6%2Fc9225c2f4d2ca43cf029933da301%2Fhuzefa.16x9.png",
            "sourceId": 2,
            "source": "Amazon Science Blog"
        },
        {
            "id": 2314,
            "title": "Apache Airflow Essential Guide",
            "url": "https://www.analyticsvidhya.com/blog/2022/08/apache-airflow-essential-guide/",
            "authors": "Vijay Sharma",
            "tags": "Airflow, Beginner, Data Engineering, Guide, Python",
            "publishedOn": "2022-08-11T00:00:00",
            "description": "Apache airflow is a free and open source platform for automating workflows' creation, scheduling, and mirroring.",
            "thumbnail": "https://cdn.analyticsvidhya.com/wp-content/uploads/2022/01/data-lake-2-adobe.jpg",
            "sourceId": 3,
            "source": "Analytics Vidhya Blog"
        },
        {
            "id": 2315,
            "title": "Dropout Regularization in Deep Learning",
            "url": "https://www.analyticsvidhya.com/blog/2022/08/dropout-regularization-in-deep-learning/",
            "authors": "Parthiban Marimuthu",
            "tags": "Deep Learning, Intermediate, Python, Technique",
            "publishedOn": "2022-08-11T00:00:00",
            "description": "This blog talks about dropout regularization that is one technique used to tackle overfitting problems in deep learning.",
            "thumbnail": "https://cdn.analyticsvidhya.com/wp-content/uploads/2021/09/45605deep_learning.jpg",
            "sourceId": 3,
            "source": "Analytics Vidhya Blog"
        },
        {
            "id": 6778,
            "title": "Realising scientists are the real superheroes",
            "url": "https://www.deepmind.com/blog/realising-scientists-are-the-real-superheroes",
            "authors": null,
            "tags": "Life at DeepMind",
            "publishedOn": "2022-08-11T00:00:00",
            "description": "Meet Edgar Du\u00e9\u00f1ez-Guzm\u00e1n, a research engineer on our Multi-Agent Research team who\u2019s drawing on knowledge of game theory, computer science, and social evolution to get AI agents working better together.",
            "thumbnail": "https://assets-global.website-files.com/621d30e84caf0be3291dbf1c/621d346e395c98fb65f1185c_brand__symbol_white.svg",
            "sourceId": 6,
            "source": "Deepmind Blog"
        },
        {
            "id": 8317,
            "title": "Deploying \ud83e\udd17 ViT on Kubernetes with TF Serving",
            "url": "https://huggingface.co/blog/deploy-tfserving-kubernetes",
            "authors": "chansung",
            "tags": null,
            "publishedOn": "2022-08-11T00:00:00",
            "description": "We\u2019re on a journey to advance and democratize artificial intelligence through open source and open science.",
            "thumbnail": "https://huggingface.co/blog/assets/94_tf_serving_kubernetes/thumb.png",
            "sourceId": 11,
            "source": "Huggingface Blog"
        },
        {
            "id": 10674,
            "title": "I spent $15 in DALL\u00b7E 2 credits creating this AI image and here\u2019s what I learned",
            "url": "https://towardsai.net/p/l/i-spent-15-in-dall%c2%b7e-2-credits-creating-this-ai-image-and-heres-what-i-learned",
            "authors": null,
            "tags": null,
            "publishedOn": "2022-08-11T00:00:00",
            "description": null,
            "thumbnail": null,
            "sourceId": 19,
            "source": "Towards AI Blog"
        },
        {
            "id": 10675,
            "title": "Using AI to Implement Vector-Based Technology in Topic Modeling",
            "url": "https://towardsai.net/p/l/using-ai-to-implement-vector-based-technology-in-topic-modeling",
            "authors": "Kirsten Jiayi Pan",
            "tags": null,
            "publishedOn": "2022-08-11T00:00:00",
            "description": "Originally published on Towards AI the World's Leading AI and Technology News and Media Company. If you are building an AI-related product or service, we invite you to consider...",
            "thumbnail": "https://cdn-images-1.medium.com/max/930/1*wOTXgnwaRKiXd-WdJgTvtw.png",
            "sourceId": 19,
            "source": "Towards AI Blog"
        },
        {
            "id": 10676,
            "title": "Why Accuracy Is Not A Good Metric For Imbalanced Data",
            "url": "https://towardsai.net/p/l/why-accuracy-is-not-a-good-metric-for-imbalanced-data",
            "authors": "Rafay Qayyum",
            "tags": null,
            "publishedOn": "2022-08-11T00:00:00",
            "description": "Originally published on Towards AI the World's Leading AI and Technology News and Media Company. If you are building an AI-related product or service, we invite you to consider...",
            "thumbnail": "https://cdn-images-1.medium.com/max/1024/0*KZhapuFAZsJK1E9a.jpeg",
            "sourceId": 19,
            "source": "Towards AI Blog"
        },
        {
            "id": 10677,
            "title": "Biggest Problem With ML Systems Today",
            "url": "https://towardsai.net/p/l/biggest-problem-with-ml-systems-today",
            "authors": "Astha Puri",
            "tags": null,
            "publishedOn": "2022-08-11T00:00:00",
            "description": "Originally published on Towards AI the World's Leading AI and Technology News and Media Company. If you are building an AI-related product or service, we invite you to consider...",
            "thumbnail": "https://cdn-images-1.medium.com/max/1024/0*2oKlrBW27MvT_jDh",
            "sourceId": 19,
            "source": "Towards AI Blog"
        },
        {
            "id": 10678,
            "title": "Is This the Way AI Gains Human Sight?",
            "url": "https://towardsai.net/p/l/is-this-the-way-ai-gains-human-sight",
            "authors": "Daniel Moriarty",
            "tags": null,
            "publishedOn": "2022-08-11T00:00:00",
            "description": "Originally published on Towards AI the World's Leading AI and Technology News and Media Company. If you are building an AI-related product or service, we invite you to consider...",
            "thumbnail": "https://cdn-images-1.medium.com/max/600/0*X52OWNQ7_wQ6AGYB",
            "sourceId": 19,
            "source": "Towards AI Blog"
        },
        {
            "id": 10679,
            "title": "Survival Analysis: Produce a Single Time-to-Event Prediction from Survival Functions",
            "url": "https://towardsai.net/p/l/survival-analysis-produce-a-single-time-to-event-prediction-from-survival-functions",
            "authors": "Yael Vilk",
            "tags": null,
            "publishedOn": "2022-08-11T00:00:00",
            "description": "Originally published on Towards AI the World's Leading AI and Technology News and Media Company. If you are building an AI-related product or service, we invite you to consider...",
            "thumbnail": "https://cdn-images-1.medium.com/max/1024/1*bpWDG9O7wS2-rfL5LAHzUw.jpeg",
            "sourceId": 19,
            "source": "Towards AI Blog"
        },
        {
            "id": 143,
            "title": "Use computer vision to measure agriculture yield with Amazon Rekognition Custom Labels",
            "url": "https://aws.amazon.com/blogs/machine-learning/use-computer-vision-to-measure-agriculture-yield-with-amazon-rekognition-custom-labels/",
            "authors": "Dhiraj Thakur, Sameer Goel",
            "tags": "Amazon Rekognition, Artificial Intelligence",
            "publishedOn": "2022-08-10T00:00:00",
            "description": "In the agriculture sector, the problem of identifying and counting the amount of fruit on trees plays an important role in crop estimation. The concept of renting and leasing a tree is becoming popular, where a tree owner leases the tree every year before the harvest based on the estimated fruit yeild. The common practice [\u2026]",
            "thumbnail": "https://d2908q01vomqb2.cloudfront.net/f1f836cb4ea6efb2a0b1b99f41ad8b103eff4b59/2022/07/26/ML-2594-image051.png",
            "sourceId": 1,
            "source": "Amazon ML Blog"
        },
        {
            "id": 144,
            "title": "Amazon SageMaker Automatic Model Tuning now supports SageMaker Training Instance Fallbacks",
            "url": "https://aws.amazon.com/blogs/machine-learning/amazon-sagemaker-automatic-model-tuning-now-supports-sagemaker-training-instance-fallbacks/",
            "authors": "Kruthi Jayasimha Rao, Bernard Jollans, Doug Mbaya",
            "tags": "Amazon Machine Learning, Amazon SageMaker",
            "publishedOn": "2022-08-10T00:00:00",
            "description": "Today Amazon SageMaker announced the support of SageMaker training instance fallbacks for Amazon SageMaker Automatic Model Tuning (AMT) that allow users to specify alternative compute resource configurations. SageMaker automatic model tuning finds the best version of a model by running many training jobs on your dataset using the\u00a0ranges of hyperparameters that you specify for your [\u2026]",
            "thumbnail": "https://d2908q01vomqb2.cloudfront.net/f1f836cb4ea6efb2a0b1b99f41ad8b103eff4b59/2022/08/10/sagemaker-automatic-model-tuning-instance-fallbacks.jpg",
            "sourceId": 1,
            "source": "Amazon ML Blog"
        }
    ]
}