{
    "hasNextPage": true,
    "data": [
        {
            "id": 5874,
            "title": "Beginners Guide to Topic Modeling in Python",
            "url": "https://www.analyticsvidhya.com/blog/2016/08/beginners-guide-to-topic-modeling-in-python/",
            "authors": "Shivam5992 Bansal",
            "tags": "Data Science, Intermediate, NLP, Python, Technique, Text, Topic Modeling, Unstructured Data, Unsupervised",
            "publishedOn": "2016-08-24T00:00:00",
            "description": "A practical guide to perform topic modeling in python. Which are the various ways to improve the results such as frequency filter, POS tag and LDA",
            "thumbnail": "https://www.analyticsvidhya.com/wp-content/uploads/2016/08/11.png"
        },
        {
            "id": 5875,
            "title": "Bringing Analytics into Indian Film Industry with Back Tracing Algorithm",
            "url": "https://www.analyticsvidhya.com/blog/2016/08/bringing-analytics-into-indian-film-industry-with-back-tracing-algorithm/",
            "authors": "guest_blog",
            "tags": "Business Analytics, Data Exploration, Entertainment, Intermediate, Resource",
            "publishedOn": "2016-08-22T00:00:00",
            "description": "Analytics in Film Industry is a comprehensive study of using big data in film industry and making predictive analysis.",
            "thumbnail": "https://www.analyticsvidhya.com/wp-content/uploads/2016/08/4.jpg"
        },
        {
            "id": 5876,
            "title": "Industry Insight \u2013 Fighting Cyber Fraud with Analytics",
            "url": "https://www.analyticsvidhya.com/blog/2016/08/industry-insight-fighting-cyber-fraud-with-analytics/",
            "authors": "guest_blog",
            "tags": "Business Analytics, Cyber Security, Intermediate, Resource, Structured Thinking",
            "publishedOn": "2016-08-15T00:00:00",
            "description": "Fighting Cyber fraud using analytics techniques & forensic tools. Recent studies have shown increasing cyber crime in various sectors.",
            "thumbnail": "https://www.analyticsvidhya.com/wp-content/uploads/2016/08/8363737128_b76782c7a2_b.jpg"
        },
        {
            "id": 5877,
            "title": "Launch of AV Casino \u2013 An Introduction to Probability",
            "url": "https://www.analyticsvidhya.com/blog/2016/08/launch-of-av-casino-an-introduction-to-probability/",
            "authors": "Kunal Jain",
            "tags": "Analytics Vidhya, Business Analytics",
            "publishedOn": "2016-08-11T00:00:00",
            "description": "We recently launched a workshop on Introduction to Probability. It is an interactive, fun based workshop which will teach basics of probability",
            "thumbnail": "https://www.analyticsvidhya.com/wp-content/uploads/2016/08/2_1.jpg"
        },
        {
            "id": 5878,
            "title": "Winner\u2019s Secrets Decoded from \u201cThe Smart Recruits\u201d",
            "url": "https://www.analyticsvidhya.com/blog/2016/08/winners-approach-smart-recruits/",
            "authors": "Kunal Jain",
            "tags": "Analytics Vidhya, Intermediate, Listicle, Machine Learning, Winners Approach",
            "publishedOn": "2016-08-11T00:00:00",
            "description": "Winners of data science competition The Smart Recruits have shared their approach and codes.",
            "thumbnail": "https://www.analyticsvidhya.com/wp-content/uploads/2016/08/pexels-photo-59197-large.jpeg"
        },
        {
            "id": 5879,
            "title": "Practicing Machine Learning Techniques in R with MLR Package",
            "url": "https://www.analyticsvidhya.com/blog/2016/08/practicing-machine-learning-techniques-in-r-with-mlr-package/",
            "authors": "avcontentteam",
            "tags": "Banking, Beginner, Classification, Libraries, Machine Learning, Programming, Project, R, Statistics, Structured Data, Supervised",
            "publishedOn": "2016-08-08T00:00:00",
            "description": "This tutorial helps beginners to get started building machine learning models in R. Learn about machine learning techniques in R with the MLR package.",
            "thumbnail": "https://www.analyticsvidhya.com/wp-content/uploads/2016/08/feat1.png"
        },
        {
            "id": 5880,
            "title": "Innovation in Analytics Education: Great Lakes using mentored learning for Online Courses",
            "url": "https://www.analyticsvidhya.com/blog/2016/08/innovation-in-analytics-education-great-lakes-using-mentored-learning-for-online-courses/",
            "authors": "Kunal Jain",
            "tags": "Business Analytics, Education, Intermediate, Resource",
            "publishedOn": "2016-08-05T00:00:00",
            "description": "Business Analytics Certificate Program by Great Lakes Institute of Management is an innovative take on online courses. In which they have combined online learning with mentorship. The key offering of the program is unique concept of mentored learning from industry experts.",
            "thumbnail": "https://www.analyticsvidhya.com/wp-content/uploads/2016/08/GL-logo.jpg"
        },
        {
            "id": 5881,
            "title": "The Evolution and Core Concepts of Deep Learning & Neural Networks",
            "url": "https://www.analyticsvidhya.com/blog/2016/08/evolution-core-concepts-deep-learning-neural-networks/",
            "authors": "guest_blog",
            "tags": "Algorithm, Beginner, Deep Learning, Machine Learning",
            "publishedOn": "2016-08-03T00:00:00",
            "description": "Brief history of neural networks in the area of Deep Learning. This article contains evolution and concepts of neural networks and deep learning.",
            "thumbnail": "https://www.analyticsvidhya.com/wp-content/uploads/2016/08/Artificial-Intelligence-Neural-Network-Nodes.jpg"
        },
        {
            "id": 5882,
            "title": "Tutorial \u2013 Data Science at Command Line with R & Python (Scikit Learn)",
            "url": "https://www.analyticsvidhya.com/blog/2016/08/tutorial-data-science-command-line-scikit-learn/",
            "authors": "guest_blog",
            "tags": "Command Line, Data Exploration, Libraries, Machine Learning, Programming, Python, R, Regression, Structured Data, Supervised",
            "publishedOn": "2016-08-01T00:00:00",
            "description": "This tutorial explains data science at the command line with python and R to build models including data visualization, exploration and machine learning.",
            "thumbnail": "https://www.analyticsvidhya.com/wp-content/uploads/2016/07/20013034233_19f520eefb_b.jpg"
        },
        {
            "id": 5883,
            "title": "Making Predictions on Test Data after Principal Component Analysis in R",
            "url": "https://www.analyticsvidhya.com/blog/2016/07/making-predictions-test-data-principal-component-analysis/",
            "authors": "avcontentteam",
            "tags": "Intermediate, Machine Learning, R",
            "publishedOn": "2016-07-28T00:00:00",
            "description": "This article explains the method of model building using principal components on test data. It uses decision tree algorithm for modeling data",
            "thumbnail": "https://www.analyticsvidhya.com/wp-content/uploads/2016/07/PCA.jpg"
        },
        {
            "id": 5884,
            "title": "How to start applying for Analytics / Data Science Masters in the US Universities?",
            "url": "https://www.analyticsvidhya.com/blog/2016/07/apply-analytics-data-science-masters-us-universities/",
            "authors": "Aarshay Jain",
            "tags": "Beginner, Big data, Business Analytics, Interview Questions, Resource",
            "publishedOn": "2016-07-25T00:00:00",
            "description": "This is a complete guide to apply for data science & analytics masters program in US which includes tips on writing GRE TOEFL exam, SOP & other details",
            "thumbnail": "https://www.analyticsvidhya.com/wp-content/uploads/2016/07/USA-Tourist-places.jpg"
        },
        {
            "id": 5885,
            "title": "12 Winning Tips to Clinch Your First Win in Data Science Competitions",
            "url": "https://www.analyticsvidhya.com/blog/2016/07/12-winning-tips-clinch-win-data-science-competitions/",
            "authors": "Kunal Jain",
            "tags": "Beginner, Listicle, Machine Learning, Resource",
            "publishedOn": "2016-07-21T00:00:00",
            "description": "Winning tips for machine learning competition which includes feature engineering, stacking, ensembling, data exploration, algorithm selection",
            "thumbnail": "https://www.analyticsvidhya.com/wp-content/uploads/2016/07/black-and-white-sport-fight-boxer-large.jpg"
        },
        {
            "id": 5886,
            "title": "20 Challenging Job Interview Puzzles which\u00a0every analyst should solve atleast once",
            "url": "https://www.analyticsvidhya.com/blog/2016/07/20-challenging-job-interview-puzzles-which-every-analyst-solve-atleast/",
            "authors": "avcontentteam",
            "tags": "Beginner, Business Analytics, Interview Questions, Interviews, Interviews, Structured Thinking",
            "publishedOn": "2016-07-21T00:00:00",
            "description": "What are the challenging puzzles asked in data science and data analyst interviews? Solve these data science puzzles using logical thinking and maths",
            "thumbnail": "https://www.analyticsvidhya.com/wp-content/uploads/2016/07/tote.jpg"
        },
        {
            "id": 5887,
            "title": "Practical Guide on Data Preprocessing in Python using Scikit Learn",
            "url": "https://www.analyticsvidhya.com/blog/2016/07/practical-guide-data-preprocessing-python-scikit-learn/",
            "authors": "Syed4194 Danish",
            "tags": "Business Analytics, Classification, Data Exploration, Intermediate, Libraries, Machine Learning, Programming, Python, Structured Data, Supervised",
            "publishedOn": "2016-07-18T00:00:00",
            "description": "Data preprocessing in python using scikit learn library that includes scaling, label encoding for preprocessing and preparing data for our models.",
            "thumbnail": "https://www.analyticsvidhya.com/wp-content/uploads/2016/07/banner.png"
        },
        {
            "id": 5888,
            "title": "Going Deeper into Regression Analysis with Assumptions, Plots & Solutions",
            "url": "https://www.analyticsvidhya.com/blog/2016/07/deeper-regression-analysis-assumptions-plots-solutions/",
            "authors": "avcontentteam",
            "tags": "Algorithm, Business Analytics, Intermediate, Machine Learning",
            "publishedOn": "2016-07-14T00:00:00",
            "description": "Regression analysis is a parametric approach in predictive modeling. Discover the plots and assumptions of regression analysis with solutions.",
            "thumbnail": "https://www.analyticsvidhya.com/wp-content/uploads/2016/07/graphic.jpg"
        },
        {
            "id": 5889,
            "title": "3 Must Know Analytical Concepts For Every\u00a0Professional / Fresher\u00a0in Analytics",
            "url": "https://www.analyticsvidhya.com/blog/2016/07/3-analytical-concepts-every-professional-fresher-in-analytics/",
            "authors": "guest_blog",
            "tags": "Business Analytics, Intermediate, Technique",
            "publishedOn": "2016-07-12T00:00:00",
            "description": "This article explains 3 analytical concepts which includes descriptive, predictive and prescriptive analytics for analytics professionals",
            "thumbnail": "https://www.analyticsvidhya.com/wp-content/uploads/2016/06/BS.png"
        },
        {
            "id": 5890,
            "title": "10 Analytics / Data Science Masters Program by Top Universities in the US",
            "url": "https://www.analyticsvidhya.com/blog/2016/07/10-analytics-data-science-top-universities-masters-usa/",
            "authors": "Aarshay Jain",
            "tags": "Beginner, Big data, Business Analytics, Courses, Education, Listicle, Machine Learning",
            "publishedOn": "2016-07-10T00:00:00",
            "description": "This article reviews top 10 masters program in analytics, data science and machine learning in US and ranked them according to parameters.",
            "thumbnail": "https://www.analyticsvidhya.com/wp-content/uploads/2016/07/droide.jpg"
        },
        {
            "id": 5891,
            "title": "Using Platt Scaling and Isotonic Regression to Minimize LogLoss Error in R",
            "url": "https://www.analyticsvidhya.com/blog/2016/07/platt-scaling-isotonic-regression-minimize-logloss-error/",
            "authors": "NSS",
            "tags": "Advanced, Machine Learning, R, Regression, Structured Data, Supervised, Technique",
            "publishedOn": "2016-07-07T00:00:00",
            "description": "This tutorial explains using isotonic regression and platt scaling to calibrate predicted probabilities to improve logloss error in data set",
            "thumbnail": "https://www.analyticsvidhya.com/wp-content/uploads/2016/07/Rplot03.png"
        },
        {
            "id": 5892,
            "title": "Tapping Twitter Sentiments: A Complete\u00a0Case-Study on 2015 Chennai Floods",
            "url": "https://www.analyticsvidhya.com/blog/2016/07/capstone-project/",
            "authors": "guest_blog",
            "tags": "Business Analytics, Classification, Intermediate, Machine Learning, NLP, Project, Python, Supervised, Text, Unstructured Data",
            "publishedOn": "2016-07-06T00:00:00",
            "description": "This case study is based on Chennai Floods 2015 and measures people's sentiments during he floods by analyzing the response on twitter.",
            "thumbnail": "https://www.analyticsvidhya.com/wp-content/uploads/2016/07/man-dog-chennai-759.jpg"
        },
        {
            "id": 5893,
            "title": "Solving Case study : Optimize the Products Price for an Online Vendor (Level : Hard)",
            "url": "https://www.analyticsvidhya.com/blog/2016/07/solving-case-study-optimize-products-price-online-vendor-level-hard/",
            "authors": "Tavish Srivastava",
            "tags": "Advanced, Business Analytics, E-Commerce, Interview Questions, Interviews, R, Resource, Structured Data, Structured Thinking",
            "publishedOn": "2016-07-04T00:00:00",
            "description": "This analytics case study is meant to optimize the product price using business and analytics approach. Structured thinking is also required",
            "thumbnail": "https://www.analyticsvidhya.com/wp-content/uploads/2016/07/ever_case-compressed.jpg"
        },
        {
            "id": 5894,
            "title": "Learning Path : Step by Step Guide for Beginners to Learn SparkR",
            "url": "https://www.analyticsvidhya.com/blog/2016/06/learning-path-step-step-guide-beginners-learn-sparkr/",
            "authors": "Shashwat.2014 Srivastava",
            "tags": "Beginner, Big data, Learning Path, R",
            "publishedOn": "2016-06-30T00:00:00",
            "description": "This article presents a step by step learning path for beginners to learn sparkR for faster computation on big data sets using R programming",
            "thumbnail": "https://www.analyticsvidhya.com/wp-content/uploads/2016/06/learning_1.jpg"
        },
        {
            "id": 5895,
            "title": "12 Free Mind Mapping Tools For a Data Scientist To Enhance Structured Thinking",
            "url": "https://www.analyticsvidhya.com/blog/2016/06/12-free-mind-mapping-tools-data-scientist-enhance-structured-thinking/",
            "authors": "avcontentteam",
            "tags": "Beginner, Business Analytics, Listicle, Resource, Structured Thinking",
            "publishedOn": "2016-06-28T00:00:00",
            "description": "This article list 12 free mind mapping tools to enhance structured thinking for a data scientist to create data maps, brainstorming and more",
            "thumbnail": "https://www.analyticsvidhya.com/wp-content/uploads/2016/06/mindmap.jpg"
        },
        {
            "id": 5896,
            "title": "Operations analytics case study (level : hard)",
            "url": "https://www.analyticsvidhya.com/blog/2016/06/operations-analytics-case-study-level-hard/",
            "authors": "Tavish Srivastava",
            "tags": "Business Analytics, Call Center, Intermediate, Resource, Structured Thinking",
            "publishedOn": "2016-06-23T00:00:00",
            "description": "In this article we solve transportation problem in operations analytics using various approach (north west approach, minumum cost & penalty cost)",
            "thumbnail": "https://www.analyticsvidhya.com/wp-content/uploads/2016/04/join.jpg"
        },
        {
            "id": 5897,
            "title": "Bayesian Statistics explained to Beginners in Simple English",
            "url": "https://www.analyticsvidhya.com/blog/2016/06/bayesian-statistics-beginners-simple-english/",
            "authors": "NSS",
            "tags": "Beginner, Probability, R, Statistics, Technique",
            "publishedOn": "2016-06-20T00:00:00",
            "description": "This article explains bayesian statistics in simple english. It explain concepts such as conditional probability, bayes theorem and inference",
            "thumbnail": "https://www.analyticsvidhya.com/wp-content/uploads/2016/06/12.jpg"
        },
        {
            "id": 5898,
            "title": "Winners of Mini DataHack (Time Series) \u2013 Approach, Codes and Solutions",
            "url": "https://www.analyticsvidhya.com/blog/2016/06/winners-mini-datahack-time-series-approach-codes-solutions/",
            "authors": "avcontentteam",
            "tags": "Business Analytics, Intermediate, Listicle, Machine Learning, Python, R, Time Series, Winners Approach",
            "publishedOn": "2016-06-17T00:00:00",
            "description": "This is the solution of mini datahack time series. The winners used xgboost, exponential smoothing time series and data exploration techniques",
            "thumbnail": "https://www.analyticsvidhya.com/wp-content/uploads/2016/06/solve.jpg"
        },
        {
            "id": 5899,
            "title": "11 Must Read Books This Summer on Internet of Things (IoT)",
            "url": "https://www.analyticsvidhya.com/blog/2016/06/11-read-books-summer-internet-iot/",
            "authors": "avcontentteam",
            "tags": "Beginner, Big data, Books, Business Analytics, IOT, Listicle",
            "publishedOn": "2016-06-16T00:00:00",
            "description": "This article lists the must read useful books on internet of things. IoT is majorly driven by abundance of data, sensors to connect devices",
            "thumbnail": "https://www.analyticsvidhya.com/wp-content/uploads/2016/06/booko-1024x683.jpg"
        },
        {
            "id": 5900,
            "title": "9 Challenges on Data Merging and Subsetting in R & Python (for beginners)",
            "url": "https://www.analyticsvidhya.com/blog/2016/06/9-challenges-data-merging-subsetting-r-python-beginner/",
            "authors": "Syed4194 Danish",
            "tags": "Beginner, Business Analytics, Data Exploration, Listicle, Programming, Python, R, Structured Data",
            "publishedOn": "2016-06-12T00:00:00",
            "description": "This article explains merging, joining, sorting, subsetting of data frames, columns, rows using practice in R and Python with various examples",
            "thumbnail": "https://www.analyticsvidhya.com/wp-content/uploads/2016/06/man.jpg"
        },
        {
            "id": 5901,
            "title": "Exclusive Python Tutorials & Talks from PyCon 2016 Portland, Oregon",
            "url": "https://www.analyticsvidhya.com/blog/2016/06/exclusive-python-tutorials-talks-pycon-2016-portland-oregon/",
            "authors": "Kunal Jain",
            "tags": "Big data, Business Analytics, Education, Intermediate, Listicle, Machine Learning, Python, Research & Technology, Videos",
            "publishedOn": "2016-06-07T00:00:00",
            "description": "This article list the best tutorial and talks on python from PyCon Conference 2016. The videos include machine learning, statistics, data etc",
            "thumbnail": "https://www.analyticsvidhya.com/wp-content/uploads/2016/06/tumblr_inline_nx1ss5EXo91tp8y64_500.png"
        },
        {
            "id": 5902,
            "title": "Getting Started with Big Data Integration using HDFS and DMX-h",
            "url": "https://www.analyticsvidhya.com/blog/2016/06/started-big-data-integration-hdfs-dmexpress/",
            "authors": "guest_blog",
            "tags": "Big data, Data Engineering, Intermediate, Libraries, Programming",
            "publishedOn": "2016-06-04T00:00:00",
            "description": "This article explains hadoop distribution file system HDFS) architecture, its components like mapreduce using DMX-h for data integration",
            "thumbnail": "https://www.analyticsvidhya.com/wp-content/uploads/2016/06/big_data_integration-1024x658.jpg"
        },
        {
            "id": 5903,
            "title": "Quick Guide to Build a Recommendation Engine in Python & R",
            "url": "https://www.analyticsvidhya.com/blog/2016/06/quick-guide-build-recommendation-engine-python/",
            "authors": "Aarshay Jain",
            "tags": "Data Science, Intermediate, Machine Learning, Project, Python, R, Recommendation, Statistics, Structured Data, Supervised, Technique, Telecom",
            "publishedOn": "2016-06-02T00:00:00",
            "description": "Building recommendation engines in python and R, learn building one using graphlab library in the field of data science and machine learning.",
            "thumbnail": "https://www.analyticsvidhya.com/wp-content/uploads/2016/06/money-card-business-credit-card-50987-large.jpeg"
        }
    ]
}